dockter/__init__.py
dockter/analyzer.py
dockter/main.py
dockter/parser.py
pydockter-1.0.0.dist-info/LICENSE
pydockter-1.0.0.dist-info/METADATA
pydockter-1.0.0.dist-info/WHEEL
pydockter-1.0.0.dist-info/entry_points.txt
pydockter-1.0.0.dist-info/top_level.txt
pydockter-1.0.0.dist-info/RECORD
