Metadata-Version: 2.1
Name: pydockter
Version: 1.0.0
Summary: dockter: The doctor for your Dockerfiles
Home-page: https://gitlab.com/gitlab-org/incubation-engineering/ai-assist/dockter
Author: Fred de Gier
Project-URL: Source, https://gitlab.com/gitlab-org/incubation-engineering/ai-assist/dockter/-/tree/main
Project-URL: Tracker, https://gitlab.com/gitlab-org/incubation-engineering/ai-assist/dockter/-/issues
Keywords: test,unittest
Classifier: Development Status :: 3 - Alpha
Classifier: Intended Audience :: Developers
Classifier: Operating System :: MacOS :: MacOS X
Classifier: Programming Language :: Python :: 3
Classifier: Programming Language :: Python :: 3 :: Only
Classifier: Programming Language :: Python :: 3.10
Classifier: Topic :: Software Development :: Libraries
Classifier: Topic :: Software Development :: Testing
Classifier: Topic :: Utilities
Classifier: Topic :: Security
Requires-Python: >=3.10
License-File: LICENSE
